bitcoinpython/__init__.py
bitcoinpython/base58.py
bitcoinpython/cli.py
bitcoinpython/crypto.py
bitcoinpython/curve.py
bitcoinpython/exceptions.py
bitcoinpython/format.py
bitcoinpython/keygen.py
bitcoinpython/transaction.py
bitcoinpython/utils.py
bitcoinpython/wallet.py
bitcoinpython/network/__init__.py
bitcoinpython/network/fees.py
bitcoinpython/network/meta.py
bitcoinpython/network/rates.py
bitcoinpython/network/services.py
bitcoinpython/network/transaction.py
tests/__init__.py
tests/samples.py
tests/test_base58.py
tests/test_curve.py
tests/test_format.py
tests/test_transaction.py
tests/test_utils.py
tests/test_wallet.py
tests/utils.py
tests/network/__init__.py
tests/network/test_fees.py
tests/network/test_meta.py
tests/network/test_rates.py
tests/network/test_services.py
bitcoinpython-0.5.3.dist-info/LICENSE.txt
bitcoinpython-0.5.3.dist-info/METADATA
bitcoinpython-0.5.3.dist-info/WHEEL
bitcoinpython-0.5.3.dist-info/entry_points.txt
bitcoinpython-0.5.3.dist-info/top_level.txt
bitcoinpython-0.5.3.dist-info/RECORD
