Metadata-Version: 2.1
Name: bitcoinpython
Version: 0.5.3
Summary: Bitcoin Cash for Python
Home-page: https://github.com/merc1er/bitcoinpython
Author: Corentin Mercier
Author-email: corentin@mercier.link
Maintainer: Corentin Mercier
Maintainer-email: corentin@mercier.link
License: MIT
Download-URL: https://github.com/merc1er/bitcoinpython/tarball/0.5.3
Keywords: bitcoin,bitcoincash,cryptocurrency,payments,tools,wallet
Platform: UNKNOWN
Classifier: Development Status :: 4 - Beta
Classifier: Intended Audience :: Developers
Classifier: Intended Audience :: End Users/Desktop
Classifier: License :: OSI Approved :: MIT License
Classifier: Natural Language :: English
Classifier: Operating System :: OS Independent
Classifier: Programming Language :: Python :: 3.5
Classifier: Programming Language :: Python :: 3.6
Classifier: Programming Language :: Python :: 3.7
Classifier: Programming Language :: Python :: Implementation :: CPython
Classifier: Programming Language :: Python :: Implementation :: PyPy
Requires-Dist: coincurve (>=4.3.0)
Requires-Dist: requests
Requires-Dist: cashaddress (==1.0.4)
Provides-Extra: cache
Requires-Dist: lmdb ; extra == 'cache'
Provides-Extra: cli
Requires-Dist: appdirs ; extra == 'cli'
Requires-Dist: click ; extra == 'cli'
Requires-Dist: privy ; extra == 'cli'
Requires-Dist: tinydb ; extra == 'cli'
